MANIFEST.in
Readme.rst
setup.py
pysmac/__init__.py
pysmac/optimize.py
pysmac/smacparse.py
pysmac/smacremote.py
pysmac/smacrunner.py
pysmac.egg-info/PKG-INFO
pysmac.egg-info/SOURCES.txt
pysmac.egg-info/dependency_links.txt
pysmac.egg-info/requires.txt
pysmac.egg-info/top_level.txt
pysmac/smac/smac-v2.08.00-development-723/smac
pysmac/smac/smac-v2.08.00-development-723/smac-validate.bat
pysmac/smac/smac-v2.08.00-development-723/smac.bat
pysmac/smac/smac-v2.08.00-development-723/lib/DomainInter.jar
pysmac/smac/smac-v2.08.00-development-723/lib/Jama-1.0.2.jar
pysmac/smac/smac-v2.08.00-development-723/lib/aeatk-src.jar
pysmac/smac/smac-v2.08.00-development-723/lib/aeatk.jar
pysmac/smac/smac-v2.08.00-development-723/lib/commons-collections-3.2.1-sources.jar
pysmac/smac/smac-v2.08.00-development-723/lib/commons-collections-3.2.1.jar
pysmac/smac/smac-v2.08.00-development-723/lib/commons-io-2.1.jar
pysmac/smac/smac-v2.08.00-development-723/lib/commons-math-2.2.jar
pysmac/smac/smac-v2.08.00-development-723/lib/commons-math3-3.2.jar
pysmac/smac/smac-v2.08.00-development-723/lib/exp4j-0.3.10.jar
pysmac/smac/smac-v2.08.00-development-723/lib/fastrf-src.jar
pysmac/smac/smac-v2.08.00-development-723/lib/fastrf.jar
pysmac/smac/smac-v2.08.00-development-723/lib/guava-14.0.1.jar
pysmac/smac/smac-v2.08.00-development-723/lib/jackson-annotations-2.3.1.jar
pysmac/smac/smac-v2.08.00-development-723/lib/jackson-core-2.3.1.jar
pysmac/smac/smac-v2.08.00-development-723/lib/jackson-databind-2.3.1.jar
pysmac/smac/smac-v2.08.00-development-723/lib/jcip-annotations-src.jar
pysmac/smac/smac-v2.08.00-development-723/lib/jcip-annotations.jar
pysmac/smac/smac-v2.08.00-development-723/lib/jcommander.jar
pysmac/smac/smac-v2.08.00-development-723/lib/jmatharray.jar
pysmac/smac/smac-v2.08.00-development-723/lib/logback-access-1.1.2.jar
pysmac/smac/smac-v2.08.00-development-723/lib/logback-classic-1.1.2.jar
pysmac/smac/smac-v2.08.00-development-723/lib/logback-core-1.1.2.jar
pysmac/smac/smac-v2.08.00-development-723/lib/numerics4j-1.3.jar
pysmac/smac/smac-v2.08.00-development-723/lib/opencsv-2.3.jar
