Metadata-Version: 1.0
Name: pysmac
Version: 0.8
Summary: python interface to the hyperparameter optimization tool SMAC.
Home-page: http://www.cs.ubc.ca/labs/beta/Projects/SMAC/
Author: Tobias Domhan (python wrapper). Frank Hutter, Holger Hoos, Kevin Leyton-Brown, Kevin Murphy and Steve Ramage (SMAC)
Author-email: domhant@informatik.uni-freiburg.de
License: SMAC is free for academic & non-commercial usage. Please contact Frank Hutter(fh@informatik.uni-freiburg.de) to discuss obtaining a license for commercial purposes.
Keywords: hyperparameter parameter optimization hyperopt bayesian smac global
Platform: UNKNOWN
